{"3": {"name": "County Council District 1", "candidates": [{"name": "Nicole Ng-A-Qui", "party": "(Prefers Democratic Party)", "total_votes": 8140, "color": "blue"}, {"name": "Nate Nehring", "party": "(Prefers Republican Party)", "total_votes": 19232, "color": "red"}, {"name": "Richard Yust", "party": "(Prefers Democratic Party)", "total_votes": 1689, "color": "yellow"}, {"name": "Write-in", "party": "Nonpartisan", "total_votes": 57, "color": "salmon"}], "ballots_cast": 29239, "voters": 109820, "overvotes": 8, "undervotes": 113}, "4": {"name": "County Council District 4", "candidates": [{"name": "Jared M. Mead", "party": "(Prefers Democrat Party)", "total_votes": 17805, "color": "blue"}, {"name": "Brenda Carrington", "party": "(Prefers Republican Party)", "total_votes": 9190, "color": "red"}, {"name": "Write-in", "party": "Nonpartisan", "total_votes": 37, "color": "yellow"}], "ballots_cast": 27252, "voters": 104637, "overvotes": 0, "undervotes": 220}, "5": {"name": "County Council District 5", "candidates": [{"name": "Brandy Donaghy", "party": "(Prefers Democratic Party)", "total_votes": 13052, "color": "blue"}, {"name": "Sam Low", "party": "(Prefers Republican Party)", "total_votes": 18176, "color": "red"}, {"name": "Write-in", "party": "Nonpartisan", "total_votes": 41, "color": "yellow"}], "ballots_cast": 31458, "voters": 109026, "overvotes": 2, "undervotes": 187}, "6": {"name": "City of Bothell Council Position 5", "candidates": [{"name": "Galen Altavas", "party": "Nonpartisan", "total_votes": 392, "color": "purple"}, {"name": "Matt Kuehn", "party": "Nonpartisan", "total_votes": 1526, "color": "green"}, {"name": "Ben Mahnkey", "party": "Nonpartisan", "total_votes": 1627, "color": "yellow"}, {"name": "Write-in", "party": "Nonpartisan", "total_votes": 13, "color": "salmon"}], "ballots_cast": 3682, "voters": 11623, "overvotes": 0, "undervotes": 124}, "7": {"name": "City of Edmonds Council Position 1", "candidates": [{"name": "Alicia Crank", "party": "Nonpartisan", "total_votes": 5832, "color": "purple"}, {"name": "Kristiana Johnson", "party": "Nonpartisan", "total_votes": 5538, "color": "green"}, {"name": "Brian Hartman", "party": "Nonpartisan", "total_votes": 1358, "color": "yellow"}, {"name": "Write-in", "party": "Nonpartisan", "total_votes": 31, "color": "salmon"}], "ballots_cast": 12999, "voters": 31279, "overvotes": 3, "undervotes": 237}, "8": {"name": "City of Edmonds Council Position 2", "candidates": [{"name": "Lora Petso", "party": "Nonpartisan", "total_votes": 2060, "color": "purple"}, {"name": "Luke Distelhorst", "party": "Nonpartisan", "total_votes": 3073, "color": "green"}, {"name": "Janelle Cass", "party": "Nonpartisan", "total_votes": 4124, "color": "yellow"}, {"name": "Will Chen", "party": "Nonpartisan", "total_votes": 3684, "color": "salmon"}, {"name": "Write-in", "party": "Nonpartisan", "total_votes": 10, "color": "wheat"}], "ballots_cast": 12999, "voters": 31279, "overvotes": 6, "undervotes": 42}, "9": {"name": "City of Everett Mayor", "candidates": [{"name": "Steve Oss", "party": "Nonpartisan", "total_votes": 2759, "color": "purple"}, {"name": "Cassie Franklin", "party": "Nonpartisan", "total_votes": 10710, "color": "green"}, {"name": "Ron Wittock", "party": "Nonpartisan", "total_votes": 463, "color": "yellow"}, {"name": "Write-in", "party": "Nonpartisan", "total_votes": 133, "color": "salmon"}], "ballots_cast": 14230, "voters": 60761, "overvotes": 5, "undervotes": 160}, "10": {"name": "City of Everett Council District 3", "candidates": [{"name": "Lacey Sauvageau", "party": "Nonpartisan", "total_votes": 606, "color": "purple"}, {"name": "Don Schwab", "party": "Nonpartisan", "total_votes": 2459, "color": "green"}, {"name": "Jacob L. Vail", "party": "Nonpartisan", "total_votes": 287, "color": "yellow"}, {"name": "Write-in", "party": "Nonpartisan", "total_votes": 21, "color": "salmon"}], "ballots_cast": 3436, "voters": 12808, "overvotes": 1, "undervotes": 62}, "11": {"name": "City of Everett Council District 5", "candidates": [{"name": "Ben Zarlingo", "party": "Nonpartisan", "total_votes": 1183, "color": "purple"}, {"name": "Kelly M. Fox", "party": "Nonpartisan", "total_votes": 629, "color": "green"}, {"name": "Demi Chatters", "party": "Nonpartisan", "total_votes": 745, "color": "yellow"}, {"name": "Write-in", "party": "Nonpartisan", "total_votes": 23, "color": "salmon"}], "ballots_cast": 2632, "voters": 12211, "overvotes": 1, "undervotes": 51}, "12": {"name": "City of Granite Falls Council Position 2", "candidates": [{"name": "David Griggs", "party": "Nonpartisan", "total_votes": 325, "color": "purple"}, {"name": "Scott Morrison", "party": "Nonpartisan", "total_votes": 181, "color": "green"}, {"name": "Michael Hagglund", "party": "Nonpartisan", "total_votes": 109, "color": "yellow"}, {"name": "Write-in", "party": "Nonpartisan", "total_votes": 6, "color": "salmon"}], "ballots_cast": 635, "voters": 2942, "overvotes": 1, "undervotes": 13}, "13": {"name": "City of Lynnwood Mayor", "candidates": [{"name": "Jim Smith", "party": "Nonpartisan", "total_votes": 1903, "color": "purple"}, {"name": "Christine Frizzell", "party": "Nonpartisan", "total_votes": 2740, "color": "green"}, {"name": "George Hurst", "party": "Nonpartisan", "total_votes": 1431, "color": "yellow"}, {"name": "Write-in", "party": "Nonpartisan", "total_votes": 10, "color": "salmon"}], "ballots_cast": 6149, "voters": 21583, "overvotes": 0, "undervotes": 65}, "14": {"name": "City of Lynnwood Council Position 1", "candidates": [{"name": "Shirley Sutton", "party": "Nonpartisan", "total_votes": 2653, "color": "purple"}, {"name": "Nick Coelho", "party": "Nonpartisan", "total_votes": 1749, "color": "green"}, {"name": "Chris Eck", "party": "Nonpartisan", "total_votes": 1511, "color": "yellow"}, {"name": "Write-in", "party": "Nonpartisan", "total_votes": 46, "color": "salmon"}], "ballots_cast": 6149, "voters": 21583, "overvotes": 2, "undervotes": 188}, "15": {"name": "City of Lynnwood Council Position 2", "candidates": [{"name": "Don Gough", "party": "Nonpartisan", "total_votes": 1917, "color": "purple"}, {"name": "Patrick Decker", "party": "Nonpartisan", "total_votes": 1920, "color": "green"}, {"name": "Naz Lashgari", "party": "Nonpartisan", "total_votes": 2080, "color": "yellow"}, {"name": "Write-in", "party": "Nonpartisan", "total_votes": 15, "color": "salmon"}], "ballots_cast": 6149, "voters": 21583, "overvotes": 2, "undervotes": 215}, "16": {"name": "City of Lynnwood Council Position 3", "candidates": [{"name": "Lisa Utter", "party": "Nonpartisan", "total_votes": 1763, "color": "purple"}, {"name": "James Rutherford", "party": "Nonpartisan", "total_votes": 1458, "color": "green"}, {"name": "Joshua Binda", "party": "Nonpartisan", "total_votes": 2705, "color": "yellow"}, {"name": "Write-in", "party": "Nonpartisan", "total_votes": 13, "color": "salmon"}], "ballots_cast": 6149, "voters": 21583, "overvotes": 1, "undervotes": 209}, "17": {"name": "City of Marysville Council Position 1", "candidates": [{"name": "Cindy Gobel", "party": "Nonpartisan", "total_votes": 4083, "color": "purple"}, {"name": "Daniel Brady", "party": "Nonpartisan", "total_votes": 1629, "color": "green"}, {"name": "Jeffrey D. Vaughan", "party": "Nonpartisan", "total_votes": 4560, "color": "yellow"}, {"name": "Write-in", "party": "Nonpartisan", "total_votes": 35, "color": "salmon"}], "ballots_cast": 10568, "voters": 43130, "overvotes": 1, "undervotes": 260}, "18": {"name": "City of Mill Creek Council Position 6", "candidates": [{"name": "Melissa Duque", "party": "Nonpartisan", "total_votes": 1873, "color": "purple"}, {"name": "Adam R. Morgan", "party": "Nonpartisan", "total_votes": 1852, "color": "green"}, {"name": "Shannon Warren", "party": "Nonpartisan", "total_votes": 140, "color": "yellow"}, {"name": "Write-in", "party": "Nonpartisan", "total_votes": 15, "color": "salmon"}], "ballots_cast": 3979, "voters": 13113, "overvotes": 3, "undervotes": 96}, "19": {"name": "City of Mukilteo Council Position 1", "candidates": [{"name": "Peter Zieve", "party": "Nonpartisan", "total_votes": 2242, "color": "purple"}, {"name": "Chris Perisho", "party": "Nonpartisan", "total_votes": 85, "color": "green"}, {"name": "Tina Over", "party": "Nonpartisan", "total_votes": 558, "color": "yellow"}, {"name": "Louis Harris", "party": "Nonpartisan", "total_votes": 2918, "color": "salmon"}, {"name": "Write-in", "party": "Nonpartisan", "total_votes": 12, "color": "wheat"}], "ballots_cast": 5863, "voters": 14989, "overvotes": 1, "undervotes": 47}, "20": {"name": "City of Mukilteo Council Position 2", "candidates": [{"name": "Kevin Stoltz", "party": "Nonpartisan", "total_votes": 2196, "color": "purple"}, {"name": "Caitlein Ryan", "party": "Nonpartisan", "total_votes": 1513, "color": "green"}, {"name": "Ayesha Riaz Khan", "party": "Nonpartisan", "total_votes": 416, "color": "yellow"}, {"name": "Tom Jordal", "party": "Nonpartisan", "total_votes": 1657, "color": "salmon"}, {"name": "Write-in", "party": "Nonpartisan", "total_votes": 13, "color": "wheat"}], "ballots_cast": 5863, "voters": 14989, "overvotes": 2, "undervotes": 66}, "21": {"name": "City of Mukilteo Council Position 3", "candidates": [{"name": "Steve Schmalz", "party": "Nonpartisan", "total_votes": 2195, "color": "purple"}, {"name": "Alex Crocco", "party": "Nonpartisan", "total_votes": 1370, "color": "green"}, {"name": "Carolyn (Dode) Carlson", "party": "Nonpartisan", "total_votes": 1363, "color": "yellow"}, {"name": "Tim Ellis", "party": "Nonpartisan", "total_votes": 797, "color": "salmon"}, {"name": "Write-in", "party": "Nonpartisan", "total_votes": 19, "color": "wheat"}], "ballots_cast": 5863, "voters": 14989, "overvotes": 1, "undervotes": 118}, "22": {"name": "City of Snohomish Mayor", "candidates": [{"name": "Linda Redmon", "party": "Nonpartisan", "total_votes": 1252, "color": "purple"}, {"name": "John T. Kartak", "party": "Nonpartisan", "total_votes": 1140, "color": "green"}, {"name": "Samuel F. King", "party": "Nonpartisan", "total_votes": 103, "color": "yellow"}, {"name": "Write-in", "party": "Nonpartisan", "total_votes": 2, "color": "salmon"}], "ballots_cast": 2542, "voters": 6750, "overvotes": 0, "undervotes": 45}, "23": {"name": "City of Snohomish Council-at-Large Position 5", "candidates": [{"name": "Kari Zimmerman", "party": "Nonpartisan", "total_votes": 815, "color": "purple"}, {"name": "Becky Perkins", "party": "Nonpartisan", "total_votes": 329, "color": "green"}, {"name": "David Flynn", "party": "Nonpartisan", "total_votes": 1227, "color": "yellow"}, {"name": "Write-in", "party": "Nonpartisan", "total_votes": 15, "color": "salmon"}], "ballots_cast": 2542, "voters": 6750, "overvotes": 0, "undervotes": 156}, "24": {"name": "City of Snohomish Council-at-Large Position 7", "candidates": [{"name": "Karen W. Guzak", "party": "Nonpartisan", "total_votes": 905, "color": "purple"}, {"name": "Steve Dana", "party": "Nonpartisan", "total_votes": 1000, "color": "green"}, {"name": "Tabitha Baty", "party": "Nonpartisan", "total_votes": 556, "color": "yellow"}, {"name": "Write-in", "party": "Nonpartisan", "total_votes": 7, "color": "salmon"}], "ballots_cast": 2542, "voters": 6750, "overvotes": 0, "undervotes": 74}, "25": {"name": "Town of Darrington Council Position 2", "candidates": [{"name": "Robert Requa", "party": "Nonpartisan", "total_votes": 80, "color": "purple"}, {"name": "Tyller C. Boomgaarden", "party": "Nonpartisan", "total_votes": 58, "color": "green"}, {"name": "Julie Ford", "party": "Nonpartisan", "total_votes": 123, "color": "yellow"}, {"name": "Write-in", "party": "Nonpartisan", "total_votes": 6, "color": "salmon"}], "ballots_cast": 270, "voters": 900, "overvotes": 1, "undervotes": 2}, "26": {"name": "Everett School District No. 2 Director-at-Large Position 4", "candidates": [{"name": "Charles Mister, Jr.", "party": "Nonpartisan", "total_votes": 4729, "color": "purple"}, {"name": "Traci Mitchell", "party": "Nonpartisan", "total_votes": 12241, "color": "green"}, {"name": "Janelle Burke", "party": "Nonpartisan", "total_votes": 3825, "color": "yellow"}, {"name": "Write-in", "party": "Nonpartisan", "total_votes": 179, "color": "salmon"}], "ballots_cast": 22063, "voters": 86752, "overvotes": 11, "undervotes": 1078}, "27": {"name": "Lake Stevens School District No. 4 Director District 4", "candidates": [{"name": "Brett Rogers", "party": "Nonpartisan", "total_votes": 2608, "color": "purple"}, {"name": "Brian Kesler", "party": "Nonpartisan", "total_votes": 2126, "color": "green"}, {"name": "Nina Kim Hanson", "party": "Nonpartisan", "total_votes": 3103, "color": "yellow"}, {"name": "Write-in", "party": "Nonpartisan", "total_votes": 38, "color": "salmon"}], "ballots_cast": 8092, "voters": 33012, "overvotes": 3, "undervotes": 214}, "28": {"name": "Marysville School District No. 25 Director District 4", "candidates": [{"name": "Clarence Shaw", "party": "Nonpartisan", "total_votes": 2053, "color": "purple"}, {"name": "Jim Ross", "party": "Nonpartisan", "total_votes": 1188, "color": "green"}, {"name": "Wade Rinehardt", "party": "Nonpartisan", "total_votes": 5210, "color": "yellow"}, {"name": "Vanessa Edwards", "party": "Nonpartisan", "total_votes": 2999, "color": "salmon"}, {"name": "Write-in", "party": "Nonpartisan", "total_votes": 47, "color": "wheat"}], "ballots_cast": 11821, "voters": 48362, "overvotes": 3, "undervotes": 321}, "29": {"name": "Northshore School District No. 417 Director District 1", "candidates": [{"name": "Brian M. Travis", "party": "Nonpartisan", "total_votes": 1835, "color": "purple"}, {"name": "Michael Albrecht", "party": "Nonpartisan", "total_votes": 1035, "color": "green"}, {"name": "Jacqueline McGourty", "party": "Nonpartisan", "total_votes": 4707, "color": "yellow"}, {"name": "Elizabeth Crowley", "party": "Nonpartisan", "total_votes": 1827, "color": "salmon"}, {"name": "Write-in", "party": "Nonpartisan", "total_votes": 19, "color": "wheat"}], "ballots_cast": 9766, "voters": 34319, "overvotes": 3, "undervotes": 340}, "30": {"name": "Northshore School District No. 417 Director District 4", "candidates": [{"name": "Katya Bautista", "party": "Nonpartisan", "total_votes": 1782, "color": "purple"}, {"name": "Sandy R. Hayes", "party": "Nonpartisan", "total_votes": 5228, "color": "green"}, {"name": "Chris Roberdeau", "party": "Nonpartisan", "total_votes": 2346, "color": "yellow"}, {"name": "Write-in", "party": "Nonpartisan", "total_votes": 21, "color": "salmon"}], "ballots_cast": 9766, "voters": 34319, "overvotes": 2, "undervotes": 387}, "31": {"name": "Northshore School District No. 417 Director District 5", "candidates": [{"name": "Amy Felt", "party": "Nonpartisan", "total_votes": 2627, "color": "purple"}, {"name": "Angela Chapman", "party": "Nonpartisan", "total_votes": 1374, "color": "green"}, {"name": "Jasmine Lee Fry", "party": "Nonpartisan", "total_votes": 1460, "color": "yellow"}, {"name": "Amy Cast", "party": "Nonpartisan", "total_votes": 3810, "color": "salmon"}, {"name": "Write-in", "party": "Nonpartisan", "total_votes": 38, "color": "wheat"}], "ballots_cast": 9766, "voters": 34319, "overvotes": 6, "undervotes": 451}, "32": {"name": "Stanwood-Camano School District No. 401 Director District 1", "candidates": [{"name": "Albert Schreiber", "party": "Nonpartisan", "total_votes": 1874, "color": "purple"}, {"name": "Gary Forslund", "party": "Nonpartisan", "total_votes": 1692, "color": "green"}, {"name": "Kevin Williams", "party": "Nonpartisan", "total_votes": 691, "color": "yellow"}, {"name": "Write-in", "party": "Nonpartisan", "total_votes": 22, "color": "salmon"}], "ballots_cast": 4460, "voters": 14508, "overvotes": 0, "undervotes": 181}, "33": {"name": "Stanwood-Camano School District No. 401 Director District 2", "candidates": [{"name": "Samantha Smith", "party": "Nonpartisan", "total_votes": 689, "color": "purple"}, {"name": "Charlotte Murry", "party": "Nonpartisan", "total_votes": 1727, "color": "green"}, {"name": "Tracy Abuhl", "party": "Nonpartisan", "total_votes": 1823, "color": "yellow"}, {"name": "Write-in", "party": "Nonpartisan", "total_votes": 15, "color": "salmon"}], "ballots_cast": 4460, "voters": 14508, "overvotes": 0, "undervotes": 206}, "34": {"name": "Fire District 5 Commissioner Position 2", "candidates": [{"name": "Dave Moon", "party": "Nonpartisan", "total_votes": 409, "color": "purple"}, {"name": "Deborah Chase", "party": "Nonpartisan", "total_votes": 594, "color": "green"}, {"name": "Misti Halverson", "party": "Nonpartisan", "total_votes": 418, "color": "yellow"}, {"name": "Doug White", "party": "Nonpartisan", "total_votes": 198, "color": "salmon"}, {"name": "Write-in", "party": "Nonpartisan", "total_votes": 5, "color": "wheat"}], "ballots_cast": 1679, "voters": 6225, "overvotes": 1, "undervotes": 54}, "2": {"name": "Fire District 5 Proposition No. 1", "candidates": [{"name": "Yes", "party": "Nonpartisan", "total_votes": 780, "color": "purple"}, {"name": "No", "party": "Nonpartisan", "total_votes": 875, "color": "green"}], "ballots_cast": 1679, "voters": 6225, "overvotes": 0, "undervotes": 24}, "35": {"name": "Fire District 21 Commissioner Position 2", "candidates": [{"name": "David D. Safford", "party": "Nonpartisan", "total_votes": 1208, "color": "purple"}, {"name": "Greg Taylor", "party": "Nonpartisan", "total_votes": 274, "color": "green"}, {"name": "Jeffrey Edmonds", "party": "Nonpartisan", "total_votes": 256, "color": "yellow"}, {"name": "Write-in", "party": "Nonpartisan", "total_votes": 13, "color": "salmon"}], "ballots_cast": 1876, "voters": 6807, "overvotes": 0, "undervotes": 125}, "36": {"name": "Alderwood Water & Wastewater Dist. Commissioner Position 2", "candidates": [{"name": "Mike Pivec", "party": "Nonpartisan", "total_votes": 6026, "color": "purple"}, {"name": "Sandra Brewer", "party": "Nonpartisan", "total_votes": 4000, "color": "green"}, {"name": "Donna Cross", "party": "Nonpartisan", "total_votes": 9581, "color": "yellow"}, {"name": "Cory Paul Christianson", "party": "Nonpartisan", "total_votes": 3324, "color": "salmon"}, {"name": "Patrick Leonetti", "party": "Nonpartisan", "total_votes": 7824, "color": "wheat"}, {"name": "Write-in", "party": "Nonpartisan", "total_votes": 80, "color": "olivedrab"}], "ballots_cast": 32678, "voters": 135506, "overvotes": 23, "undervotes": 1820}, "37": {"name": "Hospital District 2 Commissioner Position 2", "candidates": [{"name": "Rico Tessandore", "party": "Nonpartisan", "total_votes": 8385, "color": "purple"}, {"name": "Carolyn Brennan", "party": "Nonpartisan", "total_votes": 17362, "color": "green"}, {"name": "Zemach Faris", "party": "Nonpartisan", "total_votes": 6115, "color": "yellow"}, {"name": "Write-in", "party": "Nonpartisan", "total_votes": 130, "color": "salmon"}], "ballots_cast": 34496, "voters": 119175, "overvotes": 5, "undervotes": 2499}, "38": {"name": "Port of Edmonds Commissioner-at-Large Position 5", "candidates": [{"name": "Selena Killin", "party": "Nonpartisan", "total_votes": 811, "color": "purple"}, {"name": "Scott Marshall", "party": "Nonpartisan", "total_votes": 1245, "color": "green"}, {"name": "Steve Johnston", "party": "Nonpartisan", "total_votes": 4817, "color": "yellow"}, {"name": "Write-in", "party": "Nonpartisan", "total_votes": 16, "color": "salmon"}], "ballots_cast": 7389, "voters": 15697, "overvotes": 0, "undervotes": 500}, "1": {"name": "Snohomish Transportation Benefit District Proposition No. 1", "candidates": [{"name": "Yes", "party": "Nonpartisan", "total_votes": 1411, "color": "purple"}, {"name": "No", "party": "Nonpartisan", "total_votes": 1060, "color": "green"}], "ballots_cast": 2542, "voters": 6750, "overvotes": 0, "undervotes": 71}}